funcgpt/__init__.py
funcgpt/credentials.py
funcgpt/decorators.py
funcgpt/gpt.py
funcgpt/message.py
funcgpt/protocols.py
funcgpt/tokentools.py
funcgpt/wrapper.py
funcgpt/data/cl100k_base.tiktoken.bz2
funcgpt-1.1.1.dist-info/LICENSE
funcgpt-1.1.1.dist-info/METADATA
funcgpt-1.1.1.dist-info/WHEEL
funcgpt-1.1.1.dist-info/top_level.txt
funcgpt-1.1.1.dist-info/RECORD
