Metadata-Version: 2.1
Name: funcgpt
Version: 1.1.1
Summary: A library to easily create functions based on OpenAI's GPT
Author-email: Leandro Pereira de Lima e Silva <leandro@lls-software.com>
Project-URL: Homepage, https://github.com/leandropls/funcgpt
Project-URL: Bug Tracker, https://github.com/leandropls/funcgpt/issues
Classifier: Development Status :: 4 - Beta
Classifier: Intended Audience :: Developers
Classifier: License :: OSI Approved :: MIT License
Classifier: Programming Language :: Python :: 3 :: Only
Classifier: Operating System :: OS Independent
Classifier: Topic :: Software Development
Classifier: Topic :: Software Development :: Libraries
Classifier: Topic :: Software Development :: Libraries :: Python Modules
Classifier: Topic :: Utilities
Requires-Python: >=3.10
License-File: LICENSE
Requires-Dist: tiktoken (>=0.3.3)
